grid_toolkit/Mat_10_1_X_X.csv
grid_toolkit/Mat_10_2_X_X.csv
grid_toolkit/Mat_11_1_X_X.csv
grid_toolkit/Mat_11_2_X_X.csv
grid_toolkit/Mat_12_1_X_X.csv
grid_toolkit/Mat_12_2_X_X.csv
grid_toolkit/Mat_1_1_X_X.csv
grid_toolkit/Mat_1_2_X_X.csv
grid_toolkit/Mat_2_1_X_X.csv
grid_toolkit/Mat_2_2_X_X.csv
grid_toolkit/Mat_3_1_X_X.csv
grid_toolkit/Mat_3_2_X_X.csv
grid_toolkit/Mat_4_1_X_X.csv
grid_toolkit/Mat_4_2_X_X.csv
grid_toolkit/Mat_5_1_X_X.csv
grid_toolkit/Mat_5_2_X_X.csv
grid_toolkit/Mat_6_1_X_X.csv
grid_toolkit/Mat_6_2_X_X.csv
grid_toolkit/Mat_7_1_X_X.csv
grid_toolkit/Mat_7_2_X_X.csv
grid_toolkit/Mat_8_1_X_X.csv
grid_toolkit/Mat_8_2_X_X.csv
grid_toolkit/Mat_9_1_X_X.csv
grid_toolkit/Mat_9_2_X_X.csv
grid_toolkit/__init__.py
grid_toolkit/generate.py
grid_toolkit-1.0.10.dist-info/DESCRIPTION.rst
grid_toolkit-1.0.10.dist-info/METADATA
grid_toolkit-1.0.10.dist-info/RECORD
grid_toolkit-1.0.10.dist-info/WHEEL
grid_toolkit-1.0.10.dist-info/entry_points.txt
grid_toolkit-1.0.10.dist-info/metadata.json
grid_toolkit-1.0.10.dist-info/top_level.txt
