Metadata-Version: 2.0
Name: grid-toolkit
Version: 1.0.10
Summary: A toolkit for generating grid-frequency deviation scenarios over 15 minute timesteps.
Home-page: https://github.com/thmercier/grid_toolkit
Author: Thomas Mercier
Author-email: thomas.mercier(at)uclouvain.be
License: MIT
Keywords: energy grid system simulation optimization
Platform: UNKNOWN
Classifier: Development Status :: 4 - Beta
Classifier: Intended Audience :: Science/Research
Classifier: Topic :: Scientific/Engineering
Classifier: License :: OSI Approved :: MIT License
Classifier: Programming Language :: Python :: 2
Classifier: Programming Language :: Python :: 2.6
Classifier: Programming Language :: Python :: 2.7
Requires-Dist: matplotlib
Requires-Dist: numpy
Requires-Dist: pandas
Requires-Dist: pytz
Requires-Dist: scipy
Requires-Dist: statsmodels
